odoo/addons/delivery_postlogistics/README.rst
odoo/addons/delivery_postlogistics/__init__.py
odoo/addons/delivery_postlogistics/__manifest__.py
odoo/addons/delivery_postlogistics/data/barcode handbuch.PDF
odoo/addons/delivery_postlogistics/data/delivery.xml
odoo/addons/delivery_postlogistics/data/package_type.xml
odoo/addons/delivery_postlogistics/data/partner.xml
odoo/addons/delivery_postlogistics/data/product.xml
odoo/addons/delivery_postlogistics/i18n/delivery_postlogistics.pot
odoo/addons/delivery_postlogistics/i18n/es.po
odoo/addons/delivery_postlogistics/i18n/it.po
odoo/addons/delivery_postlogistics/migrations/18.0.1.0.0/pre-migration.py
odoo/addons/delivery_postlogistics/models/__init__.py
odoo/addons/delivery_postlogistics/models/delivery_carrier.py
odoo/addons/delivery_postlogistics/models/delivery_carrier_template_option.py
odoo/addons/delivery_postlogistics/models/postlogistics_license.py
odoo/addons/delivery_postlogistics/models/res_partner.py
odoo/addons/delivery_postlogistics/models/stock_move.py
odoo/addons/delivery_postlogistics/models/stock_package_type.py
odoo/addons/delivery_postlogistics/models/stock_picking.py
odoo/addons/delivery_postlogistics/models/stock_quant_package.py
odoo/addons/delivery_postlogistics/postlogistics/__init__.py
odoo/addons/delivery_postlogistics/postlogistics/web_service.py
odoo/addons/delivery_postlogistics/readme/CONFIGURE.md
odoo/addons/delivery_postlogistics/readme/CONTRIBUTORS.md
odoo/addons/delivery_postlogistics/readme/CREDITS.md
odoo/addons/delivery_postlogistics/readme/DESCRIPTION.md
odoo/addons/delivery_postlogistics/readme/ROADMAP.md
odoo/addons/delivery_postlogistics/security/ir.model.access.csv
odoo/addons/delivery_postlogistics/static/description/icon.svg
odoo/addons/delivery_postlogistics/static/description/index.html
odoo/addons/delivery_postlogistics/static/img/postlogistics-logo.jpg
odoo/addons/delivery_postlogistics/tests/__init__.py
odoo/addons/delivery_postlogistics/tests/common.py
odoo_addon_delivery_postlogistics-18.0.1.3.1.1.dist-info/METADATA
odoo_addon_delivery_postlogistics-18.0.1.3.1.1.dist-info/WHEEL
odoo_addon_delivery_postlogistics-18.0.1.3.1.1.dist-info/top_level.txt
odoo_addon_delivery_postlogistics-18.0.1.3.1.1.dist-info/RECORD
