Metadata-Version: 2.1
Name: odoo-addon-delivery_postlogistics
Version: 18.0.1.3.1.1
Requires-Python: >=3.10
Requires-Dist: odoo-addon-delivery_carrier_info==18.0.*
Requires-Dist: odoo-addon-delivery_carrier_option==18.0.*
Requires-Dist: odoo-addon-delivery_carrier_shipping_label==18.0.*
Requires-Dist: odoo==18.0.*
Requires-Dist: openupgradelib
Summary: Print PostLogistics shipping labels using the Barcode web service
Home-page: https://github.com/OCA/delivery-carrier
License: AGPL-3
Author: Camptocamp,Odoo Community Association (OCA)
Author-email: support@odoo-community.org
Classifier: Programming Language :: Python
Classifier: Framework :: Odoo
Classifier: Framework :: Odoo :: 18.0
Classifier: License :: OSI Approved :: GNU Affero General Public License v3
